backtest/webapp.py
webappPP-1.2.3.dist-info/LICENSE
webappPP-1.2.3.dist-info/METADATA
webappPP-1.2.3.dist-info/WHEEL
webappPP-1.2.3.dist-info/entry_points.txt
webappPP-1.2.3.dist-info/top_level.txt
webappPP-1.2.3.dist-info/RECORD
