Metadata-Version: 2.1
Name: webappPP
Version: 1.2.3
Summary: Algorithm for finance
Home-page: UNKNOWN
License: MIT
Platform: UNKNOWN
Requires-Dist: pandas
Requires-Dist: numpy
Requires-Dist: pandas-datareader
Requires-Dist: scipy
Requires-Dist: Flask
Requires-Dist: seaborn
